mixdiff/__init__.py
mixdiff/canvas.py
mixdiff/extrasmixin.py
mixdiff/imgtools.py
mixdiff/tiling.py
mixdiff-1.1.5.dist-info/LICENSE
mixdiff-1.1.5.dist-info/METADATA
mixdiff-1.1.5.dist-info/WHEEL
mixdiff-1.1.5.dist-info/top_level.txt
mixdiff-1.1.5.dist-info/RECORD
