Metadata-Version: 2.1
Name: mixdiff
Version: 1.1.5
Summary: Mixture of Diffusers for scene composition and high resolution image generation .
Home-page: https://github.com/albarji/mixture-of-diffusers
Author: Alvaro Barbero
License: MIT
Keywords: artificial-intelligence,deep-learning,diffusion-models
Classifier: Development Status :: 1 - Planning
Classifier: Environment :: GPU :: NVIDIA CUDA
Classifier: Intended Audience :: Science/Research
Classifier: License :: OSI Approved :: MIT License
Classifier: Operating System :: Unix
Classifier: Programming Language :: Python :: 3.8
Classifier: Programming Language :: Python :: 3.9
Classifier: Programming Language :: Python :: 3.10
Classifier: Topic :: Artistic Software
Classifier: Topic :: Multimedia :: Graphics
License-File: LICENSE
Requires-Dist: numpy (<2,>=1.19)
Requires-Dist: tqdm (<5,>=4.62)
Requires-Dist: scipy (==1.10.*)
Requires-Dist: diffusers[torch] (==0.16.*)
Requires-Dist: ftfy (==6.1.*)
Requires-Dist: gitpython (==3.1.*)
Requires-Dist: ligo-segments (==1.4.*)
Requires-Dist: torch (==2.0.*)
Requires-Dist: torchvision (==0.15.*)
Requires-Dist: transformers (==4.29.*)
